{"category": "Drama", "movies": [{"title": "600 Miles ", "rating": "R"}, {"title": "A Hologram for the King", "rating": "R"}, {"title": "Being Charlie ", "rating": "R"}, {"title": "Choice, The ", "rating": "PG-13"}, {"title": "Dark Horse, The ", "rating": "R"}, {"title": "Dear Eleanor ", "rating": "PG-13"}, {"title": "Demolition ", "rating": "R"}, {"title": "Dog Lover, The ", "rating": "PG"}, {"title": "Eddie the Eagle ", "rating": "PG-13"}, {"title": "Emma's Chance ", "rating": "PG"}, {"title": "Eye in the Sky ", "rating": "R"}, {"title": "Free State of Jones", "rating": "R"}, {"title": "God's Not Dead 2", "rating": "PG"}, {"title": "Hello, My Name Is Doris ", "rating": "R"}, {"title": "I Saw the Light ", "rating": "R"}, {"title": "Joy ", "rating": "PG-13"}, {"title": "Last Days in the Desert", "rating": "PG-13"}, {"title": "Lobster, The", "rating": "R"}, {"title": "Louder than Bombs ", "rating": "R"}, {"title": "Man Who Knew Infinity, The", "rating": "PG-13"}, {"title": "Miles Ahead ", "rating": "R"}, {"title": "Miracles From Heaven with Bonus Featurette ", "rating": "PG"}, {"title": "Never Back Down: No Surrender ", "rating": "R"}, {"title": "No Men Beyond this Point ", "rating": "NR"}, {"title": "Only Yesterday {2016 re-release} ", "rating": "PG"}, {"title": "Quitters ", "rating": "TV-14"}, {"title": "Race (2016) ", "rating": "PG-13"}, {"title": "Sing Street ", "rating": "PG-13"}, {"title": "Take Me to the River (2016) ", "rating": "TV-14"}, {"title": "Young Messiah, The ", "rating": "PG-13"}]}